potato/__init__.py
potato/ahha.py
potato/hoho.py
potato/main.py
progressive_mypy/__init__.py
progressive_mypy/main.py
tests/__init__.py
tests/test_smoke.py
progressive_mypy-0.0.0.dist-info/LICENSE
progressive_mypy-0.0.0.dist-info/METADATA
progressive_mypy-0.0.0.dist-info/WHEEL
progressive_mypy-0.0.0.dist-info/top_level.txt
progressive_mypy-0.0.0.dist-info/RECORD
